{
  "wavelengths": [
    400,
    420,
    440,
    450,
    460,
    480,
    500,
    520,
    540,
    560,
    580,
    600,
    620,
    640,
    660,
    680,
    700,
    720,
    740
  ],
  "channels": {
    "cw": {
      "description": "Cool White 5000K",
      "peak": 5000,
      "values": [
        0.02,
        0.08,
        0.15,
        0.2,
        0.22,
        0.25,
        0.3,
        0.35,
        0.38,
        0.4,
        0.35,
        0.28,
        0.2,
        0.12,
        0.08,
        0.05,
        0.03,
        0.01,
        0.0
      ]
    },
    "ww": {
      "description": "Warm White 3000K",
      "peak": 3000,
      "values": [
        0.01,
        0.05,
        0.1,
        0.15,
        0.18,
        0.2,
        0.25,
        0.3,
        0.35,
        0.38,
        0.4,
        0.35,
        0.3,
        0.22,
        0.15,
        0.1,
        0.06,
        0.03,
        0.01
      ]
    },
    "bl": {
      "description": "Blue 450nm",
      "peak": 450,
      "values": [
        0.1,
        0.3,
        0.6,
        1.0,
        0.8,
        0.4,
        0.15,
        0.05,
        0.02,
        0.01,
        0.0,
        0.0,
        0.0,
        0.0,
        0.0,
        0.0,
        0.0,
        0.0,
        0.0
      ]
    },
    "rd": {
      "description": "Red 660nm",
      "peak": 660,
      "values": [
        0.0,
        0.0,
        0.0,
        0.0,
        0.0,
        0.0,
        0.0,
        0.01,
        0.02,
        0.03,
        0.05,
        0.1,
        0.25,
        0.6,
        1.0,
        0.7,
        0.35,
        0.1,
        0.02
      ]
    }
  },
  "metadata": {
    "source": "Default approximation",
    "created": "2026-01-20",
    "note": "These are typical spectral distributions for horticultural LEDs. Replace with actual measured data from PAR sensor for accuracy."
  },
  "schemaVersion": "1.0.0"
}
