{
  "vendor": "Code3",
  "deviceFamily": "dynamic-light",
  "proxy": {
    "server": {
      "script": "server-charlie.js",
      "host": "127.0.0.1",
      "port": 8091
    },
    "controller": {
      "host": "192.168.2.80",
      "port": 3000
    },
    "endpoints": {
      "health": {
        "method": "GET",
        "path": "/healthz",
        "description": "Confirms the server ↔ controller link and controller URL."
      },
      "devices": {
        "method": "GET",
        "path": "/api/devicedatas",
        "description": "Returns device list with id, name, status, and online fields."
      },
      "deviceControl": {
        "method": "PATCH",
        "path": "/api/devicedatas/device/:id",
        "description": "Controls light power state and HEX payload."
      },
      "plans": {
        "method": "POST",
        "path": "/controller/plans",
        "description": "Publishes lighting recipes generated by the Excel bridge."
      },
      "schedule": {
        "method": "POST",
        "path": "/controller/sched",
        "description": "Publishes lighting schedules generated by the Excel bridge."
      }
    }
  },
  "deviceIds": {
    "2": "F00001",
    "3": "F00002",
    "4": "F00003",
    "5": "F00005",
    "6": "F00004"
  },
  "hexPayload": {
  "format": "[CW][WW][BL][RD][00][00]",
  "channelRange": "Grow3: 0-64 decimal (00-40 hex). Legacy: 0-255 (00-FF) deprecated.",
    "examples": {
      "safeOn": {
        "status": "on",
        "value": "1D1D1D1D0000",
        "perScale": {
          "00-40": "1D1D1D1D0000",
          "00-FF-LEGACY": "737373730000"
        },
        "notes": "45% across channels (Grow3: 0x1D=29 decimal)"
      },
      "allOff": {
        "status": "off",
        "value": null
      },
      "red100": {
        "status": "on",
        "value": "000000400000",
        "perScale": {
          "00-40": "000000400000",
          "00-FF-LEGACY": "000000FF0000"
        }
      },
      "blue50": {
        "status": "on",
        "value": "000020000000",
        "perScale": {
          "00-40": "000020000000",
          "00-FF-LEGACY": "000080000000"
        }
      }
    }
  },
  "excelBridge": {
    "workbook": "/home/greenreach/LightRecipes.xlsx",
    "sheets": ["Lights", "Recipes", "Schedules"],
    "conversion": "round((pct / 100) * maxByte)",
    "publishesTo": ["/controller/plans", "/controller/sched"],
    "defaultSafeOn": "1D1D1D1D0000",
    "safeOnByScale": {
      "00-40": "1D1D1D1D0000",
      "00-FF-LEGACY": "737373730000"
    }
  },
  "verificationChecklist": [
    "curl -s http://127.0.0.1:8091/healthz → expect 200 OK",
    "curl -s http://127.0.0.1:8091/api/devicedatas → verify Code3 IDs",
    "curl -X PATCH -H 'Content-Type: application/json' -d '{\"status\":\"on\",\"value\":\"1D1D1D1D0000\"}' http://127.0.0.1:8091/api/devicedatas/device/2",
    "Confirm UI spectrum matches controller state",
    "Ensure POST /controller/plans and /controller/sched return 200"
  ]
}
